MANIFEST.in
README.md
colab_a11y_utils.py
requirements.txt
setup.py
colab_a11y_utils.egg-info/PKG-INFO
colab_a11y_utils.egg-info/SOURCES.txt
colab_a11y_utils.egg-info/dependency_links.txt
colab_a11y_utils.egg-info/not-zip-safe
colab_a11y_utils.egg-info/requires.txt
colab_a11y_utils.egg-info/top_level.txt