Metadata-Version: 2.1
Name: colab-a11y-utils
Version: 0.0.3
Summary: Tools to improve Google Colab experience for screen reader users
Home-page: https://github.com/hassaku/colab-a11y-utils
Author: hassaku
Author-email: hassaku.apps@gmail.com
License: MIT
Keywords: accessibility google-colab screen-reader visually-impaired
Platform: UNKNOWN
